{
  "assessmentCollection": [
    {
      "id": "5414af61-36d4-41e2-817f-fc61a0f904ea",
      "memberid": "ef928222-1c14-45b4-bef5-f6f73140ff03",
      "date": "03/10/2018, 5:01:33 PM",
      "weight": "123.3",
      "chest": "45",
      "thigh": "12.5",
      "upperarm": "23.3",
      "waist": "32",
      "hip": "38",
      "trend": false
    },
    {
      "id": "287abd89-8a48-467e-8add-9280ed215e71",
      "memberid": "6c9b6401-92b4-4c2b-8b01-8f463804ca71",
      "date": "5/26/2019, 5:14:49 PM",
      "weight": "60",
      "chest": "32.5",
      "thigh": "20.5",
      "upperarm": "12",
      "waist": "32",
      "hip": "38",
      "trend": true
    },
    {
      "id": "77d3a81a-5273-4cc6-8fc4-2450b763e477",
      "memberid": "6c9b6401-92b4-4c2b-8b01-8f463804ca71",
      "date": "6/26/2019, 5:15:27 PM",
      "weight": "61",
      "chest": "33",
      "thigh": "20.5",
      "upperarm": "12",
      "waist": "3.2",
      "hip": "38",
      "trend": false
    },
    {
      "id": "15667965-da94-434c-912f-842bd4b14cb0",
      "memberid": "6c9b6401-92b4-4c2b-8b01-8f463804ca71",
      "date": "7/26/2019, 5:17:28 PM",
      "weight": "59",
      "chest": "33",
      "thigh": "20",
      "upperarm": "11.9",
      "waist": "32",
      "hip": "38",
      "trend": true
    },
    {
      "id": "20a2a123-0cc8-4272-b4fa-038522eea00b",
      "memberid": "6c9b6401-92b4-4c2b-8b01-8f463804ca71",
      "date": "8/26/2019, 5:31:53 PM",
      "weight": "59",
      "chest": "33",
      "thigh": "20",
      "upperarm": "12",
      "waist": "32",
      "hip": "38",
      "trend": true
    },
    {
      "id": "f7a98420-d2a5-11ea-84e9-01fa9a8e47de",
      "memberid": "ef928222-1c14-45b4-bef5-f6f73140ff03",
      "date": "7/30/2020, 8:48:05 PM",
      "weight": "79",
      "chest": "105",
      "thigh": "20",
      "upperarm": "30",
      "waist": "70",
      "hip": "44",
      "trend": true
    },
    {
      "id": "8f0ba2d0-d2a6-11ea-b2f5-9f1223153998",
      "memberid": "ef928222-1c14-45b4-bef5-f6f73140ff03",
      "date": "7/30/2020, 8:52:19 PM",
      "weight": "69",
      "chest": "80",
      "thigh": "39",
      "upperarm": "20",
      "waist": "60",
      "hip": "34",
      "trend": true
    },
    {
      "id": "0a18df50-eecd-11ea-a486-33f8585850a9",
      "memberid": "ef928222-1c14-45b4-bef5-f6f73140ff03",
      "date": "9/4/2020, 4:38:19 PM",
      "weight": "65",
      "chest": "105",
      "thigh": "30",
      "upperarm": "30",
      "waist": "70",
      "hip": "80",
      "trend": true
    },
    {
      "id": "0a3ddc60-eee1-11ea-9155-8f9699bf2fdd",
      "memberid": "ef928222-1c14-45b4-bef5-f6f73140ff03",
      "date": "9/4/2020, 7:01:29 PM",
      "weight": "60",
      "chest": "105",
      "thigh": "33",
      "upperarm": "15",
      "waist": "60",
      "hip": "33",
      "trend": true
    }
  ]
}